[
  {"timestamp":"2025-11-01T08:00:00Z","enc":{"temp":28.4,"voltage":360.2,"current":12.5,"soc":95.1,"soh":98.2}},
  {"timestamp":"2025-11-01T08:00:03Z","enc":{"temp":28.7,"voltage":360.6,"current":15.2,"soc":94.9,"soh":98.1}},
  {"timestamp":"2025-11-01T08:00:06Z","enc":{"temp":29.1,"voltage":361.0,"current":20.8,"soc":94.6,"soh":98.1}},
  {"timestamp":"2025-11-01T08:00:09Z","enc":{"temp":29.8,"voltage":361.5,"current":28.5,"soc":94.2,"soh":98.0}},
  {"timestamp":"2025-11-01T08:00:12Z","enc":{"temp":30.4,"voltage":362.2,"current":35.1,"soc":93.8,"soh":97.9}},
  {"timestamp":"2025-11-01T08:00:15Z","enc":{"temp":31.1,"voltage":363.0,"current":42.3,"soc":93.3,"soh":97.8}},
  {"timestamp":"2025-11-01T08:00:18Z","enc":{"temp":32.0,"voltage":363.9,"current":55.8,"soc":92.8,"soh":97.6}},
  {"timestamp":"2025-11-01T08:00:21Z","enc":{"temp":33.5,"voltage":365.2,"current":68.2,"soc":92.0,"soh":97.4}},
  {"timestamp":"2025-11-01T08:00:24Z","enc":{"temp":34.9,"voltage":367.1,"current":82.4,"soc":91.1,"soh":97.1}},
  {"timestamp":"2025-11-01T08:00:27Z","enc":{"temp":36.2,"voltage":369.0,"current":95.6,"soc":90.0,"soh":96.8}},
  {"timestamp":"2025-11-01T08:00:30Z","enc":{"temp":37.8,"voltage":370.8,"current":110.4,"soc":88.6,"soh":96.4}},
  {"timestamp":"2025-11-01T08:00:33Z","enc":{"temp":39.6,"voltage":372.6,"current":125.7,"soc":86.9,"soh":95.9}},
  {"timestamp":"2025-11-01T08:00:36Z","enc":{"temp":41.5,"voltage":374.1,"current":138.9,"soc":85.0,"soh":95.3}},
  {"timestamp":"2025-11-01T08:00:39Z","enc":{"temp":43.2,"voltage":375.4,"current":145.2,"soc":83.1,"soh":94.6}},
  {"timestamp":"2025-11-01T08:00:42Z","enc":{"temp":45.0,"voltage":376.2,"current":152.6,"soc":80.9,"soh":93.9}},
  {"timestamp":"2025-11-01T08:00:45Z","enc":{"temp":46.8,"voltage":377.0,"current":160.5,"soc":78.5,"soh":93.1}},
  {"timestamp":"2025-11-01T08:00:48Z","enc":{"temp":47.6,"voltage":378.5,"current":158.2,"soc":76.2,"soh":92.5}},
  {"timestamp":"2025-11-01T08:00:51Z","enc":{"temp":46.1,"voltage":377.6,"current":140.0,"soc":74.9,"soh":92.0}},
  {"timestamp":"2025-11-01T08:00:54Z","enc":{"temp":44.0,"voltage":376.0,"current":120.2,"soc":73.8,"soh":91.6}},
  {"timestamp":"2025-11-01T08:00:57Z","enc":{"temp":41.5,"voltage":374.0,"current":98.5,"soc":73.2,"soh":91.3}},
  {"timestamp":"2025-11-01T08:01:00Z","enc":{"temp":39.0,"voltage":372.2,"current":78.0,"soc":73.0,"soh":91.1}},
  {"timestamp":"2025-11-01T08:01:03Z","enc":{"temp":36.8,"voltage":370.0,"current":60.2,"soc":73.1,"soh":91.0}},
  {"timestamp":"2025-11-01T08:01:06Z","enc":{"temp":34.9,"voltage":368.1,"current":45.8,"soc":73.4,"soh":91.0}},
  {"timestamp":"2025-11-01T08:01:09Z","enc":{"temp":33.2,"voltage":366.5,"current":32.4,"soc":73.8,"soh":91.0}},
  {"timestamp":"2025-11-01T08:01:12Z","enc":{"temp":31.0,"voltage":365.2,"current":18.5,"soc":74.3,"soh":91.1}}
]
